pygraph_sp-2026.3.dist-info/METADATA
pygraph_sp-2026.3.dist-info/WHEEL
graph_sp/__init__.py
graph_sp/graph_sp.cpython-312-darwin.so
pygraph_sp-2026.3.dist-info/RECORD
