Metadata-Version: 2.1
Name: pygraph-sp
Version: 2026.3
Summary: A pure Rust graph executor supporting implicit node connections, branching, and config sweeps
Keywords: graph,dag,execution,pipeline,workflow
Home-Page: https://github.com/briday1/graph-sp
Author: briday1 <your-email@example.com>
Author-email: briday1 <your-email@example.com>
License: MIT
Requires-Python: >=3.8
Project-URL: Source Code, https://github.com/briday1/graph-sp
